robocorp_dialog/Dialog/Python.Runtime.dll
robocorp_dialog/Dialog/VCRUNTIME140.dll
robocorp_dialog/Dialog/_asyncio.pyd
robocorp_dialog/Dialog/_bz2.pyd
robocorp_dialog/Dialog/_ctypes.pyd
robocorp_dialog/Dialog/_decimal.pyd
robocorp_dialog/Dialog/_hashlib.pyd
robocorp_dialog/Dialog/_lzma.pyd
robocorp_dialog/Dialog/_multiprocessing.pyd
robocorp_dialog/Dialog/_overlapped.pyd
robocorp_dialog/Dialog/_queue.pyd
robocorp_dialog/Dialog/_socket.pyd
robocorp_dialog/Dialog/_ssl.pyd
robocorp_dialog/Dialog/api-ms-win-core-console-l1-1-0.dll
robocorp_dialog/Dialog/api-ms-win-core-datetime-l1-1-0.dll
robocorp_dialog/Dialog/api-ms-win-core-debug-l1-1-0.dll
robocorp_dialog/Dialog/api-ms-win-core-errorhandling-l1-1-0.dll
robocorp_dialog/Dialog/api-ms-win-core-fibers-l1-1-0.dll
robocorp_dialog/Dialog/api-ms-win-core-file-l1-1-0.dll
robocorp_dialog/Dialog/api-ms-win-core-file-l1-2-0.dll
robocorp_dialog/Dialog/api-ms-win-core-file-l2-1-0.dll
robocorp_dialog/Dialog/api-ms-win-core-handle-l1-1-0.dll
robocorp_dialog/Dialog/api-ms-win-core-heap-l1-1-0.dll
robocorp_dialog/Dialog/api-ms-win-core-interlocked-l1-1-0.dll
robocorp_dialog/Dialog/api-ms-win-core-libraryloader-l1-1-0.dll
robocorp_dialog/Dialog/api-ms-win-core-localization-l1-2-0.dll
robocorp_dialog/Dialog/api-ms-win-core-memory-l1-1-0.dll
robocorp_dialog/Dialog/api-ms-win-core-namedpipe-l1-1-0.dll
robocorp_dialog/Dialog/api-ms-win-core-processenvironment-l1-1-0.dll
robocorp_dialog/Dialog/api-ms-win-core-processthreads-l1-1-0.dll
robocorp_dialog/Dialog/api-ms-win-core-processthreads-l1-1-1.dll
robocorp_dialog/Dialog/api-ms-win-core-profile-l1-1-0.dll
robocorp_dialog/Dialog/api-ms-win-core-rtlsupport-l1-1-0.dll
robocorp_dialog/Dialog/api-ms-win-core-string-l1-1-0.dll
robocorp_dialog/Dialog/api-ms-win-core-synch-l1-1-0.dll
robocorp_dialog/Dialog/api-ms-win-core-synch-l1-2-0.dll
robocorp_dialog/Dialog/api-ms-win-core-sysinfo-l1-1-0.dll
robocorp_dialog/Dialog/api-ms-win-core-timezone-l1-1-0.dll
robocorp_dialog-0.5.3.dist-info/entry_points.txt
robocorp_dialog-0.5.3.dist-info/LICENSE
robocorp_dialog-0.5.3.dist-info/WHEEL
robocorp_dialog-0.5.3.dist-info/METADATA
robocorp_dialog-0.5.3.dist-info/RECORD
